ibevent/__init__.py
ibevent/events.py
ibevent/hooks.py
ibevent-0.2.0.dist-info/METADATA
ibevent-0.2.0.dist-info/WHEEL
ibevent-0.2.0.dist-info/RECORD
